{
    "vm_type": "kvm",
    "hostname": "brave-gig-2.localdomain",
    "node_ip": "xx.xxx.xx.xx",
    "node_alias": "v1111",
    "node_location": "US, XXXX",
    "node_location_id": "USCA_9",
    "node_datacenter": "US: XXXX",
    "location_ipv6_ready": false,
    "plan": "kvmv3-100g-512m-1000m-xx-xxxx",
    "plan_monthly_data": 3000000000,
    "monthly_data_multiplier": 1,
    "plan_disk": 10000000,
    "plan_ram": 500000,
    "plan_swap": 0,
    "plan_max_ipv6s": 0,
    "os": "ubuntu-20.04-x86_64",
    "email": "johndoe@bandwagon.com",
    "data_counter": 1000000000,
    "data_next_reset": 100000000,
    "ip_addresses": [
        "xx.xxx.xxx.xx"
    ],
    "private_ip_addresses": [],
    "ip_nullroutes": [],
    "iso1": null,
    "iso2": null,
    "available_isos": [
        "almalinux-8.4-x86_64-minimal.iso",
        "almalinux-8.5-x86_64-boot.iso",
        "almalinux-9.0-x86_64-boot.iso",
        "almalinux-9.0-x86_64-minimal.iso",
        "alpine-standard-3.12.1-x86_64.iso",
        "alpine-standard-3.9.4-x86.iso",
        "alpine-standard-3.9.4-x86_64.iso",
        "altlinux-regular-rescue-20190313-i586.iso",
        "altlinux-regular-rescue-20190313-x86_64.iso",
        "archlinux-2019.03.01-x86_64.iso",
        "archlinux-2020.07.01-x86_64.iso",
        "centOS-7-x86_64-Minimal-1810.iso",
        "centOS-8.1.1911-x86_64-boot.iso",
        "centOS-8.1.1911-x86_64-dvd1.iso",
        "centOS-Stream-9-20220126.0-x86_64-boot.iso",
        "centos-6.10-x86_64-LiveDVD.iso",
        "centos-7-x86_64-LiveGNOME-1810.iso",
        "centos-stream-8-x86_64-20211214-boot.iso",
        "centos-stream-9-20211222.0-x86_64-boot.iso",
        "debian-10.0.0-amd64-netinst.iso",
        "debian-10.3.0-amd64-netinst.iso",
        "debian-10.6.0-amd64-netinst.iso",
        "debian-11.0.0-amd64-netinst.iso",
        "debian-9.9.0-amd64-netinst.iso",
        "debian-9.9.0-i386-netinst.iso",
        "debian-live-7.11.0-amd64-gnome-desktop.iso",
        "debian-live-7.11.0-i386-gnome-desktop.iso",
        "debian-live-7.11.0-i386-rescue.iso",
        "debian-live-8.11.0-amd64-gnome-desktop.iso",
        "debian-live-8.11.0-i386-gnome-desktop.iso",
        "debian-live-9.8.0-amd64-gnome.iso",
        "debian-live-9.8.0-i386-gnome.iso",
        "fedora-coreos-32.20201004.3.0-live.x86_64.iso",
        "fedora-server-dvd-x86_64-29-1.2.iso",
        "fedora-server-dvd-x86_64-30-1.2.iso",
        "fedora-server-dvd-x86_64-36-1.5.iso",
        "fedora-server-netinst-x86_64-29-1.2.iso",
        "fedora-server-netinst-x86_64-30-1.2.iso",
        "fedora-server-netinst-x86_64-36-1.5.iso"
    ],
    "plan_private_network_available": false,
    "location_private_network_available": true,
    "rdns_api_available": true,
    "ptr": {
        "xx.xxx.xxx.xx": null
    },
    "suspended": false,
    "policy_violation": false,
    "suspension_count": null,
    "total_abuse_points": 0,
    "max_abuse_points": 1000,
    "error": 0
}